audiologic/__init__.py
audiologic/audio.py
audiologic/utils.py
audiologic-0.1.1.dist-info/LICENSE
audiologic-0.1.1.dist-info/METADATA
audiologic-0.1.1.dist-info/WHEEL
audiologic-0.1.1.dist-info/top_level.txt
audiologic-0.1.1.dist-info/RECORD
