Metadata-Version: 2.1
Name: audiologic
Version: 0.1.1
Summary: Python utilities to process and predict on audio attributes
Author-email: Ty Martz <jacksontmartz@gmail.com>
Requires-Python: >=3.8
License-File: LICENSE
